src/htrc_topicexplorer/add_pagenos.py
src/htrc_topicexplorer/ob_ids.py
src/htrc_topicexplorer/release.py
src/htrc_topicexplorer/setup.py
src/htrc_topicexplorer/docs/conf.py
src/htrc_topicexplorer/ipynb/corpus.tmpl.py
src/htrc_topicexplorer/topicexplorer/__init__.py
src/htrc_topicexplorer/topicexplorer/__main__.py
src/htrc_topicexplorer/topicexplorer/cluster.py
src/htrc_topicexplorer/topicexplorer/config.py
src/htrc_topicexplorer/topicexplorer/debug.py
src/htrc_topicexplorer/topicexplorer/demo.py
src/htrc_topicexplorer/topicexplorer/etag.py
src/htrc_topicexplorer/topicexplorer/export.py
src/htrc_topicexplorer/topicexplorer/export_html.py
src/htrc_topicexplorer/topicexplorer/init.py
src/htrc_topicexplorer/topicexplorer/metadata.py
src/htrc_topicexplorer/topicexplorer/notebook.py
src/htrc_topicexplorer/topicexplorer/prep.py
src/htrc_topicexplorer/topicexplorer/server.py
src/htrc_topicexplorer/topicexplorer/tezimport.py
src/htrc_topicexplorer/topicexplorer/train.py
src/htrc_topicexplorer/topicexplorer/update.py
src/htrc_topicexplorer/topicexplorer/version.py
src/htrc_topicexplorer/topicexplorer/extensions/__init__.py
src/htrc_topicexplorer/topicexplorer/extensions/ap.py
src/htrc_topicexplorer/topicexplorer/extensions/bibtex.py
src/htrc_topicexplorer/topicexplorer/extensions/htrc.py
src/htrc_topicexplorer/topicexplorer/extensions/htrc_features.py
src/htrc_topicexplorer/topicexplorer/extensions/inpho.py
src/htrc_topicexplorer/topicexplorer/extensions/jeff.py
src/htrc_topicexplorer/topicexplorer/extensions/jeffcombo.py
src/htrc_topicexplorer/topicexplorer/extensions/oldbailey.py
src/htrc_topicexplorer/topicexplorer/extensions/sep.py
src/htrc_topicexplorer/topicexplorer/extensions/title.py
src/htrc_topicexplorer/topicexplorer/lib/__init__.py
src/htrc_topicexplorer/topicexplorer/lib/chinese.py
src/htrc_topicexplorer/topicexplorer/lib/color.py
src/htrc_topicexplorer/topicexplorer/lib/hathitrust.py
src/htrc_topicexplorer/topicexplorer/lib/mmseg.py
htrc_topicexplorer-1.0b3.dist-info/METADATA
htrc_topicexplorer-1.0b3.dist-info/WHEEL
htrc_topicexplorer-1.0b3.dist-info/licenses/LICENSE.txt
htrc_topicexplorer-1.0b3.dist-info/RECORD
