Metadata-Version: 2.1
Name: htrc_topicexplorer
Version: 1.0b3
Summary: HTRC rework of the InPHO Topic Explorer tool.
Project-URL: Homepage, https://github.com/htrc/topic-explorer
Project-URL: Bug Tracker, https://github.com/htrc/topic-explorer/issues
Author-email: Damien Thomas <damien.thomas.0214@gmail.com>, Samitha Liyanage <shliyana@indiana.edu>
License-File: LICENSE.txt
Classifier: Development Status :: 4 - Beta
Classifier: Environment :: Web Environment
Classifier: Framework :: Bottle
Classifier: Intended Audience :: Science/Research
Classifier: License :: OSI Approved :: MIT License
Classifier: Operating System :: OS Independent
Classifier: Programming Language :: Python
Classifier: Programming Language :: Python :: 2
Classifier: Programming Language :: Python :: 3
Classifier: Topic :: Internet :: WWW/HTTP :: Dynamic Content
Classifier: Topic :: Scientific/Engineering :: Artificial Intelligence
Classifier: Topic :: Scientific/Engineering :: Visualization
Classifier: Topic :: Software Development :: User Interfaces
Classifier: Topic :: Text Processing :: Linguistic
Requires-Python: >=3.6
